README.rst
certsrv.py
setup.py
certsrv.egg-info/PKG-INFO
certsrv.egg-info/SOURCES.txt
certsrv.egg-info/dependency_links.txt
certsrv.egg-info/requires.txt
certsrv.egg-info/top_level.txt