Metadata-Version: 2.1
Name: certsrv
Version: 2.1.0
Summary: A Python client for the Microsoft AD Certificate Services web page
Home-page: https://github.com/magnuswatn/certsrv
Author: Magnus Watn
License: MIT
Keywords: ad adcs certsrv pki certificate
Platform: UNKNOWN
Classifier: Development Status :: 5 - Production/Stable
Classifier: Intended Audience :: System Administrators
Classifier: Intended Audience :: Developers
Classifier: License :: OSI Approved :: MIT License
Classifier: Operating System :: POSIX :: Linux
Classifier: Programming Language :: Python :: 2
Classifier: Programming Language :: Python :: 2.7
Classifier: Programming Language :: Python :: 3
Classifier: Programming Language :: Python :: 3.4
Classifier: Programming Language :: Python :: 3.5
Classifier: Programming Language :: Python :: 3.6
Classifier: Topic :: Internet :: WWW/HTTP
Classifier: Topic :: Security
Classifier: Topic :: Software Development :: Libraries
Classifier: Topic :: System :: Systems Administration
Provides-Extra: ntlm
